{"stats":{"minecraft:crafted":{"minecraft:oak_planks":2,"minecraft:crafting_table":1,"minecraft:wooden_pickaxe":1,"minecraft:cooked_chicken":1,"biomesoplenty:maple_planks":5,"minecraft:furnace":1,"butchersdelightfoods:cookedsheepshank":1,"minecraft:stone_axe":1,"butchersdelightfoods:cooked_leg_cow":1,"minecraft:air":44,"butcher:bonebutchersknife":1,"minecraft:stick":2,"minecraft:iron_ingot":4,"minecraft:iron_pickaxe":1,"minecraft:stone_pickaxe":1,"minecraft:wooden_axe":1},"minecraft:mined":{"minecraft:oak_sapling":1,"minecraft:crafting_table":3,"minecraft:copper_ore":6,"biomesoplenty:sprout":4,"minecraft:furnace":2,"butchersdelight:deadcowblock":2,"minecraft:iron_ore":4,"treechop:chopped_log":3,"minecraft:grass":4,"minecraft:coal_ore":15,"minecraft:oak_log":2,"minecraft:lantern":1,"farm_and_charm:wild_strawberries":1,"minecraft:stone":22,"minecraft:oak_leaves":3,"minecraft:fern":2,"soulsweapons:verglas_ore":2},"minecraft:custom":{"minecraft:interact_with_furnace":14,"minecraft:mob_kills":3,"minecraft:interact_with_crafting_table":7,"minecraft:time_since_death":29814,"minecraft:time_since_rest":29814,"minecraft:sprint_one_cm":58368,"minecraft:damage_taken":206,"minecraft:walk_one_cm":101647,"minecraft:drop":12,"minecraft:damage_dealt":780,"minecraft:swim_one_cm":469,"minecraft:fly_one_cm":64794,"minecraft:open_chest":3,"minecraft:crouch_one_cm":1871,"minecraft:play_time":29814,"minecraft:sneak_time":755,"minecraft:walk_under_water_one_cm":3803,"minecraft:jump":464,"minecraft:walk_on_water_one_cm":721,"minecraft:total_world_time":29814,"minecraft:fall_one_cm":10061},"minecraft:picked_up":{"minecraft:crafting_table":3,"minecraft:feather":2,"butchersdelightfoods:legcow":1,"minecraft:chicken":1,"minecraft:oak_log":2,"minecraft:lantern":1,"minecraft:raw_copper":20,"butchersdelight:deadchiken":1,"minecraft:bone":2,"butchersdelight:dead_cow":5,"minecraft:wheat_seeds":3,"biomesoplenty:maple_log":5,"minecraft:beef":2,"brewery:whiskey_cristelwalker":2,"minecraft:furnace":2,"minecraft:stick":8,"minecraft:raw_iron":4,"farm_and_charm:strawberry_seeds":2,"butchersdelight:cow_hide":1,"biomesoplenty:orange_maple_sapling":6,"minecraft:spruce_sapling":7,"minecraft:spruce_log":15,"beachparty:rubber_ring_pelican":2,"butchersdelight:sheephide":2,"butchersdelight:deadsheep":2,"epicfight:glove":2,"soulsweapons:verglas":2,"butchersdelightfoods:sheepshank":1,"minecraft:oak_sapling":3,"minecraft:mutton":1,"minecraft:white_wool":2,"minecraft:coal":29,"minecraft:cobblestone":21},"minecraft:dropped":{"butchersdelight:dead_cow":1,"minecraft:wheat_seeds":3,"brewery:whiskey_cristelwalker":1,"minecraft:feather":1,"farm_and_charm:strawberry_seeds":2,"minecraft:wooden_axe":1,"epicfight:glove":1,"minecraft:stone_pickaxe":1,"minecraft:wooden_pickaxe":1},"minecraft:killed":{"minecraft:skeleton":1,"minecraft:sheep":2},"minecraft:used":{"minecraft:stone_pickaxe":37,"brewery:whiskey_cristelwalker":2,"minecraft:wooden_pickaxe":3,"butchersdelightfoods:cookedsheepshank":1,"minecraft:cooked_chicken":1,"butchersdelightfoods:cooked_leg_cow":1,"minecraft:crafting_table":3,"minecraft:wooden_axe":1,"butcher:bonebutchersknife":1,"soul_like_armors_reworked:dagger":13,"minecraft:lantern":1,"minecraft:iron_pickaxe":15,"epicfight:glove":5,"minecraft:stone_axe":17,"brewery:beer_mug":1,"minecraft:furnace":2,"minecraft:oak_sapling":3,"beachparty:rubber_ring_pelican":1}},"DataVersion":3465}